{
  "schema": 1,
  "updatedAt": "2026-07-23T17:40:21.472Z",
  "items": [
    {
      "id": "9668da3f35591de81008",
      "title": "Jet Greaves Signs a 3-Year, $15.00M Contract with the Columbus Blue Jackets",
      "publishedAt": "2026-07-23T13:43:09.000Z",
      "category": "Contract",
      "url": "https://puckpedia.com/signing/10757?utm_source=email&utm_medium=email&utm_campaign=signing&utm_content=primary"
    },
    {
      "id": "fab204a943417bdb2af7",
      "title": "Patrick Kane Signs a 2-Year, $16.00M Contract with the Chicago Blackhawks",
      "publishedAt": "2026-07-23T13:09:10.000Z",
      "category": "Contract",
      "url": "https://puckpedia.com/signing/10756?utm_source=email&utm_medium=email&utm_campaign=signing&utm_content=primary"
    },
    {
      "id": "39d15363e227f3287b87",
      "title": "Joey Larson Signs a 2-Year, $1.75M Contract with the New York Islanders",
      "publishedAt": "2026-07-22T23:46:08.000Z",
      "category": "Contract",
      "url": "https://puckpedia.com/signing/10755?utm_source=email&utm_medium=email&utm_campaign=signing&utm_content=primary"
    },
    {
      "id": "65b0f463fd60b0482a10",
      "title": "Danton Heinen Signs a 1-Year, $1.00M Contract with the Columbus Blue Jackets",
      "publishedAt": "2026-07-22T22:04:10.000Z",
      "category": "Contract",
      "url": "https://puckpedia.com/signing/10754?utm_source=email&utm_medium=email&utm_campaign=signing&utm_content=primary"
    },
    {
      "id": "b396d234bff1b6395347",
      "title": "Jason Robertson Signs a 1-Year, $12.00M Contract with the Dallas Stars",
      "publishedAt": "2026-07-22T00:12:08.000Z",
      "category": "Contract",
      "url": "https://puckpedia.com/signing/10753?utm_source=email&utm_medium=email&utm_campaign=signing&utm_content=primary"
    },
    {
      "id": "b3c2ae22f134817f806f",
      "title": "Mikulas Hovorka Signs a 1-Year, $850K Contract with the Florida Panthers",
      "publishedAt": "2026-07-21T23:44:10.000Z",
      "category": "Contract",
      "url": "https://puckpedia.com/signing/10752?utm_source=email&utm_medium=email&utm_campaign=signing&utm_content=primary"
    },
    {
      "id": "fcc2dcb9af28f1cb2c15",
      "title": "John Marino Signs an 8-Year, $54.00M Contract with the Utah Mammoth",
      "publishedAt": "2026-07-21T15:39:10.000Z",
      "category": "Contract",
      "url": "https://puckpedia.com/signing/10751?utm_source=email&utm_medium=email&utm_campaign=signing&utm_content=primary"
    },
    {
      "id": "0da0b7c3b9fb04449a3e",
      "title": "Georgii Merkulov Signs a 1-Year, $850K Contract with the Colorado Avalanche",
      "publishedAt": "2026-07-20T23:44:09.000Z",
      "category": "Contract",
      "url": "https://puckpedia.com/signing/10750?utm_source=email&utm_medium=email&utm_campaign=signing&utm_content=primary"
    },
    {
      "id": "2d6bde33c4fd2d1728a4",
      "title": "Jared Davidson Signs a 1-Year, $850K Contract with the Montreal Canadiens",
      "publishedAt": "2026-07-20T17:15:11.000Z",
      "category": "Contract",
      "url": "https://puckpedia.com/signing/10749?utm_source=email&utm_medium=email&utm_campaign=signing&utm_content=primary"
    },
    {
      "id": "4416dc7a995b318f3758",
      "title": "Hunter McKown Signs a 1-Year, $850K Contract with the Montreal Canadiens",
      "publishedAt": "2026-07-20T16:11:10.000Z",
      "category": "Contract",
      "url": "https://puckpedia.com/signing/10748?utm_source=email&utm_medium=email&utm_campaign=signing&utm_content=primary"
    },
    {
      "id": "e50b76f943dcb6ed4b44",
      "title": "Connor Bedard Signs a 5-Year, $75.00M Contract with the Chicago Blackhawks",
      "publishedAt": "2026-07-18T20:34:10.000Z",
      "category": "Contract",
      "url": "https://puckpedia.com/signing/10747?utm_source=email&utm_medium=email&utm_campaign=signing&utm_content=primary"
    },
    {
      "id": "c190a52ab55edce7a5a3",
      "title": "Jamie Drysdale Signs a 4-Year, $26.00M Contract with the Philadelphia Flyers",
      "publishedAt": "2026-07-17T18:36:10.000Z",
      "category": "Contract",
      "url": "https://puckpedia.com/signing/10746?utm_source=email&utm_medium=email&utm_campaign=signing&utm_content=primary"
    },
    {
      "id": "4180e752f4c0cd0dc649",
      "title": "Viktor Neuchev Signs a 1-Year, $850K Contract with the Carolina Hurricanes",
      "publishedAt": "2026-07-17T04:02:10.000Z",
      "category": "Contract",
      "url": "https://puckpedia.com/signing/10745?utm_source=email&utm_medium=email&utm_campaign=signing&utm_content=primary"
    },
    {
      "id": "18108467a4ffefe112cb",
      "title": "Henrik Tikkanen Signs a 1-Year, $850K Contract with the New York Islanders",
      "publishedAt": "2026-07-17T01:28:08.000Z",
      "category": "Contract",
      "url": "https://puckpedia.com/signing/10744?utm_source=email&utm_medium=email&utm_campaign=signing&utm_content=primary"
    },
    {
      "id": "69a444dbb7621ae88ba0",
      "title": "Kirby Dach Signs a 1-Year, $3.60M Contract with the Montreal Canadiens",
      "publishedAt": "2026-07-16T21:05:09.000Z",
      "category": "Contract",
      "url": "https://puckpedia.com/signing/10743?utm_source=email&utm_medium=email&utm_campaign=signing&utm_content=primary"
    },
    {
      "id": "67da2c7958624f784a93",
      "title": "Connor McMichael Signs a 6-Year, $40.50M Contract with the St. Louis Blues",
      "publishedAt": "2026-07-16T20:55:09.000Z",
      "category": "Contract",
      "url": "https://puckpedia.com/signing/10742?utm_source=email&utm_medium=email&utm_campaign=signing&utm_content=primary"
    },
    {
      "id": "ff6e88b96d14ab784bb6",
      "title": "Trevor Zegras Signs a 4-Year, $36.50M Contract with the Philadelphia Flyers",
      "publishedAt": "2026-07-16T02:02:10.000Z",
      "category": "Contract",
      "url": "https://puckpedia.com/signing/10741?utm_source=email&utm_medium=email&utm_campaign=signing&utm_content=primary"
    },
    {
      "id": "e1b0026393c6c25d814e",
      "title": "Alberts Smits Signs a 3-Year, $3.23M Contract with the New York Rangers",
      "publishedAt": "2026-07-15T23:59:07.000Z",
      "category": "Contract",
      "url": "https://puckpedia.com/signing/10740?utm_source=email&utm_medium=email&utm_campaign=signing&utm_content=primary"
    },
    {
      "id": "b66a4be93a5bf00b97f2",
      "title": "Marcus Nordmark Signs a 3-Year, $3.23M Contract with the Anaheim Ducks",
      "publishedAt": "2026-07-15T23:57:09.000Z",
      "category": "Contract",
      "url": "https://puckpedia.com/signing/10739?utm_source=email&utm_medium=email&utm_campaign=signing&utm_content=primary"
    },
    {
      "id": "6089ec04b4d238f4c97d",
      "title": "William H?kansson Signs a 3-Year, $2.99M Contract with the Carolina Hurricanes",
      "publishedAt": "2026-07-15T20:06:09.000Z",
      "category": "Contract",
      "url": "https://puckpedia.com/signing/10738?utm_source=email&utm_medium=email&utm_campaign=signing&utm_content=primary"
    },
    {
      "id": "bbd89a4fe65943e99905",
      "title": "Cole Perfetti Signs a 5-Year, $30.00M Contract with the Winnipeg Jets",
      "publishedAt": "2026-07-15T19:57:09.000Z",
      "category": "Contract",
      "url": "https://puckpedia.com/signing/10737?utm_source=email&utm_medium=email&utm_campaign=signing&utm_content=primary"
    },
    {
      "id": "0490519d5480a571ebcb",
      "title": "Juho Piiparinen Signs a 3-Year, $3.23M Contract with the Vegas Golden Knights",
      "publishedAt": "2026-07-15T18:52:08.000Z",
      "category": "Contract",
      "url": "https://puckpedia.com/signing/10736?utm_source=email&utm_medium=email&utm_campaign=signing&utm_content=primary"
    },
    {
      "id": "cf7556a6d6f2161c5ea2",
      "title": "Elton Hermansson Signs a 3-Year, $3.23M Contract with the Los Angeles Kings",
      "publishedAt": "2026-07-15T17:26:10.000Z",
      "category": "Contract",
      "url": "https://puckpedia.com/signing/10735?utm_source=email&utm_medium=email&utm_campaign=signing&utm_content=primary"
    },
    {
      "id": "3cecc7f4d170ff5e55ad",
      "title": "Anthony Mantha Signs a 2-Year, $9.50M Contract with the New Jersey Devils",
      "publishedAt": "2026-07-15T13:16:10.000Z",
      "category": "Contract",
      "url": "https://puckpedia.com/signing/10733?utm_source=email&utm_medium=email&utm_campaign=signing&utm_content=primary"
    },
    {
      "id": "4cea9c3cbf1631084566",
      "title": "Anthony Mantha Signs a 2-Year, $9.50M Contract with the Pittsburgh Penguins",
      "publishedAt": "2026-07-15T12:59:09.000Z",
      "category": "Contract",
      "url": "https://puckpedia.com/signing/10733?utm_source=email&utm_medium=email&utm_campaign=signing&utm_content=primary"
    },
    {
      "id": "8089a56047ad8f6e5409",
      "title": "Oliver Suvanto Signs a 3-Year, $3.23M Contract with the Washington Capitals",
      "publishedAt": "2026-07-15T01:15:09.000Z",
      "category": "Contract",
      "url": "https://puckpedia.com/signing/10732?utm_source=email&utm_medium=email&utm_campaign=signing&utm_content=primary"
    },
    {
      "id": "8c4f78cf599dd0314e1b",
      "title": "Malte Gustafsson Signs a 3-Year, $3.23M Contract with the New York Islanders",
      "publishedAt": "2026-07-14T16:24:16.000Z",
      "category": "Contract",
      "url": "https://puckpedia.com/signing/10731?utm_source=email&utm_medium=email&utm_campaign=signing&utm_content=primary"
    },
    {
      "id": "d5c73d506fd2c62690a6",
      "title": "Nicholas Robertson Signs a 2-Year, $6.50M Contract with the Pittsburgh Penguins",
      "publishedAt": "2026-07-14T16:23:37.000Z",
      "category": "Contract",
      "url": "https://puckpedia.com/signing/10729?utm_source=email&utm_medium=email&utm_campaign=signing&utm_content=primary"
    },
    {
      "id": "7fab61a0c39fd718f2f5",
      "title": "Nicholas Robertson Signs a 2-Year, $6.50M Contract with the Pittsburgh Penguins",
      "publishedAt": "2026-07-14T16:23:15.000Z",
      "category": "Contract",
      "url": "https://puckpedia.com/signing/10730?utm_source=email&utm_medium=email&utm_campaign=signing&utm_content=primary"
    },
    {
      "id": "1e76e656a871b4538071",
      "title": "Ronald Attard Signs a 1-Year, $850K Contract with the Detroit Red Wings",
      "publishedAt": "2026-07-14T16:23:06.000Z",
      "category": "Contract",
      "url": "https://puckpedia.com/signing/10728?utm_source=email&utm_medium=email&utm_campaign=signing&utm_content=primary"
    }
  ]
}